basic_http/__init__.py
basic_http/connection.py
basic_http/http.py
basic_http/session.py
basic_http/cookies/__init__.py
basic_http/cookies/cookies.py
basic_http/cookies/cookies_util.py
basic_http/data_structures/__init__.py
basic_http/data_structures/header.py
basic_http/data_structures/multikey.py
basic_http/data_structures/request.py
basic_http/data_structures/response.py
basic_http/exceptions/__init__.py
basic_http/exceptions/cookies.py
basic_http/exceptions/http_reader.py
basic_http/exceptions/request_response.py
basic_http/exceptions/session.py
basic_http/exceptions/structures.py
basic_http/user_agents/__init__.py
basic_http/user_agents/user_agent.py
basic_http/util/__init__.py
basic_http/util/forms.py
basic_http/util/networking.py
basic_http/util/response_parser.py
basic_http-0.0.4b0.dist-info/LICENSE
basic_http-0.0.4b0.dist-info/METADATA
basic_http-0.0.4b0.dist-info/WHEEL
basic_http-0.0.4b0.dist-info/top_level.txt
basic_http-0.0.4b0.dist-info/RECORD
