Metadata-Version: 2.1
Name: basic-http
Version: 0.0.4b0
Summary: Python 3 http package
Home-page: https://github.com/m3sserschmitt/basic-http.git
Author: Romulus-Emanuel Ruja
Author-email: romulus-emanuel.ruja@tutanota.com
License: UNKNOWN
Platform: UNKNOWN
Classifier: Operating System :: POSIX :: Linux
Classifier: Programming Language :: Python :: 3
Classifier: License :: OSI Approved :: MIT License
Classifier: Operating System :: OS Independent
Classifier: Natural Language :: English
Requires-Python: >=3.6
